{
  "generator-jhipster": {
    "applicationType": "monolith",
    "gitHubOrganization": "DinuIoan",
    "baseName": "LoginApp",
    "packageName": "ro.login",
    "serverPort": 8080,
    "serviceDiscoveryType": false,
    "authenticationType": "session",
    "uaaBaseName": "../uaa",
    "hibernateCache": "ehcache",
    "clusteredHttpSession": false,
    "websocket": false,
    "databaseType": "sql",
    "devDatabaseType": "mysql",
    "prodDatabaseType": "mysql",
    "searchEngine": false,
    "enableSwaggerCodegen": false,
    "messageBroker": false,
    "buildTool": "maven",
    "enableSocialSignIn": false,
    "useSass": false,
    "clientPackageManager": "yarn",
    "testFrameworks": [],
    "enableTranslation": false,
    "nativeLanguage": "en",
    "languages": [
      "en"
    ],
    "clientFramework": "angularX",
    "jhipsterVersion": "4.10.0",
    "packageFolder": "ro/login",
    "rememberMeKey": "fb9105221ffb37ca4240bfaea3f498d33d7ea815",
    "jhiPrefix": "jhi"
  }
}